Simpler_Kokoro/__init__.py
Simpler_Kokoro/__main__.py
Simpler_Kokoro/simpler_kokoro.py
simpler_kokoro-1.2.1.dist-info/licenses/LICENSE
simpler_kokoro-1.2.1.dist-info/METADATA
simpler_kokoro-1.2.1.dist-info/WHEEL
simpler_kokoro-1.2.1.dist-info/top_level.txt
simpler_kokoro-1.2.1.dist-info/RECORD
