Metadata-Version: 2.4
Name: Simpler_Kokoro
Version: 1.2.1
Summary: A package to make kokoro simpler to work with
Author: WilleIshere
License-Expression: GPL-3.0
Project-URL: Homepage, https://github.com/WilleIshere/SimplerKokoro
Project-URL: Issues, https://github.com/WilleIshere/SimplerKokoro/issues
Classifier: Programming Language :: Python :: 3
Classifier: Operating System :: OS Independent
Requires-Python: >=3.10
License-File: LICENSE
Requires-Dist: kokoro>=0.9.4
Requires-Dist: soundfile>=0.13.1
Requires-Dist: torch>=2.7.1
Requires-Dist: huggingface_hub>=0.33.4
Dynamic: license-file
